{
  "StoreUrl": "https://cloud.uipath.com/centepezpjpe/DefaultTenant/dataservice_/entities",
  "Entities": [
    {
      "Id": "41c0188a-2e95-f011-b3cd-002248a46af2",
      "Name": "Sontu",
      "DisplayName": "Sontu",
      "Description": "",
      "CreateTime": "2025-09-19T07:59:17.79Z",
      "UpdateTime": "2025-09-19T07:59:17.843Z",
      "Fields": [
        {
          "Id": "4bc0188a-2e95-f011-b3cd-002248a46af2",
          "Name": "Name",
          "DisplayName": "Name",
          "Description": "",
          "CreateTime": "2025-09-19T07:59:17.847Z",
          "UpdateTime": "2025-09-19T07:59:17.847Z",
          "SqlType": {
            "Name": "NVARCHAR",
            "LengthLimit": 200,
            "MaxValue": null,
            "MinValue": null,
            "DecimalPrecision": null
          },
          "IsSystemField": false,
          "IsRequired": false,
          "ReferenceEntity": null,
          "ReferenceType": "ManyToOne",
          "FieldDisplayType": "Basic",
          "ReferenceChoiceSet": null,
          "IsAttachment": false
        },
        {
          "Id": "5482702c-8e70-47e4-a64f-57e9b88161cb",
          "Name": "UpdateTime",
          "DisplayName": "UpdateTime",
          "Description": "System built-in field",
          "CreateTime": "2025-09-19T07:59:17.807Z",
          "UpdateTime": "2025-09-19T07:59:17.807Z",
          "SqlType": {
            "Name": "DATETIMEOFFSET",
            "LengthLimit": null,
            "MaxValue": null,
            "MinValue": null,
            "DecimalPrecision": null
          },
          "IsSystemField": true,
          "IsRequired": false,
          "ReferenceEntity": null,
          "ReferenceType": "ManyToOne",
          "FieldDisplayType": "Basic",
          "ReferenceChoiceSet": null,
          "IsAttachment": false
        },
        {
          "Id": "baedab98-2444-441d-9c0c-a98488989811",
          "Name": "Id",
          "DisplayName": "Id",
          "Description": "System built-in field",
          "CreateTime": "2025-09-19T07:59:17.807Z",
          "UpdateTime": "2025-09-19T07:59:17.807Z",
          "SqlType": {
            "Name": "UNIQUEIDENTIFIER",
            "LengthLimit": null,
            "MaxValue": null,
            "MinValue": null,
            "DecimalPrecision": null
          },
          "IsSystemField": true,
          "IsRequired": true,
          "ReferenceEntity": null,
          "ReferenceType": "ManyToOne",
          "FieldDisplayType": "Basic",
          "ReferenceChoiceSet": null,
          "IsAttachment": false
        },
        {
          "Id": "66f16dde-5834-4539-b919-aee5074d1413",
          "Name": "UpdatedBy",
          "DisplayName": "UpdatedBy",
          "Description": "System built-in field",
          "CreateTime": "2025-09-19T07:59:17.807Z",
          "UpdateTime": "2025-09-19T07:59:17.807Z",
          "SqlType": {
            "Name": "UNIQUEIDENTIFIER",
            "LengthLimit": null,
            "MaxValue": null,
            "MinValue": null,
            "DecimalPrecision": null
          },
          "IsSystemField": true,
          "IsRequired": false,
          "ReferenceEntity": {
            "Name": "SystemUser"
          },
          "ReferenceType": "ManyToOne",
          "FieldDisplayType": "Relationship",
          "ReferenceChoiceSet": null,
          "IsAttachment": false
        },
        {
          "Id": "b148a8da-08a7-4798-87b0-e38d8c0d92d1",
          "Name": "CreateTime",
          "DisplayName": "CreateTime",
          "Description": "System built-in field",
          "CreateTime": "2025-09-19T07:59:17.807Z",
          "UpdateTime": "2025-09-19T07:59:17.807Z",
          "SqlType": {
            "Name": "DATETIMEOFFSET",
            "LengthLimit": null,
            "MaxValue": null,
            "MinValue": null,
            "DecimalPrecision": null
          },
          "IsSystemField": true,
          "IsRequired": true,
          "ReferenceEntity": null,
          "ReferenceType": "ManyToOne",
          "FieldDisplayType": "Basic",
          "ReferenceChoiceSet": null,
          "IsAttachment": false
        },
        {
          "Id": "c9148bb7-5d6d-419c-9631-f5a7d37bb305",
          "Name": "CreatedBy",
          "DisplayName": "CreatedBy",
          "Description": "System built-in field",
          "CreateTime": "2025-09-19T07:59:17.807Z",
          "UpdateTime": "2025-09-19T07:59:17.807Z",
          "SqlType": {
            "Name": "UNIQUEIDENTIFIER",
            "LengthLimit": null,
            "MaxValue": null,
            "MinValue": null,
            "DecimalPrecision": null
          },
          "IsSystemField": true,
          "IsRequired": true,
          "ReferenceEntity": {
            "Name": "SystemUser"
          },
          "ReferenceType": "ManyToOne",
          "FieldDisplayType": "Relationship",
          "ReferenceChoiceSet": null,
          "IsAttachment": false
        }
      ],
      "RecordCount": 0,
      "EntityType": "Entity"
    },
    {
      "Id": "39c0188a-2e95-f011-b3cd-002248a46af2",
      "Name": "SystemUser",
      "DisplayName": "System Users",
      "Description": "Contains Automation Cloud users and groups that have ever had roles assigned, or accessed Data Service",
      "CreateTime": "2025-09-19T07:59:17.69Z",
      "UpdateTime": "2025-09-19T07:59:17.69Z",
      "Fields": [
        {
          "Id": "ee9ea9d6-ce54-4202-91b1-537ab4cf1810",
          "Name": "Id",
          "DisplayName": "Id",
          "Description": "System built-in field",
          "CreateTime": "2025-09-19T07:59:17.707Z",
          "UpdateTime": "2025-09-19T07:59:17.707Z",
          "SqlType": {
            "Name": "UNIQUEIDENTIFIER",
            "LengthLimit": null,
            "MaxValue": null,
            "MinValue": null,
            "DecimalPrecision": null
          },
          "IsSystemField": true,
          "IsRequired": true,
          "ReferenceEntity": null,
          "ReferenceType": "ManyToOne",
          "FieldDisplayType": "Basic",
          "ReferenceChoiceSet": null,
          "IsAttachment": false
        },
        {
          "Id": "e0bcda61-3641-45f3-98c9-6c251420ee25",
          "Name": "Type",
          "DisplayName": "Type",
          "Description": "System built-in field",
          "CreateTime": "2025-09-19T07:59:17.707Z",
          "UpdateTime": "2025-09-19T07:59:17.707Z",
          "SqlType": {
            "Name": "INT",
            "LengthLimit": null,
            "MaxValue": 9007199254740991.0,
            "MinValue": -9007199254740991.0,
            "DecimalPrecision": null
          },
          "IsSystemField": true,
          "IsRequired": true,
          "ReferenceEntity": null,
          "ReferenceType": "ManyToOne",
          "FieldDisplayType": "ChoiceSetSingle",
          "ReferenceChoiceSet": {
            "Name": "UserType"
          },
          "IsAttachment": false
        },
        {
          "Id": "02ec56e9-d074-4c74-ad80-6e19c2fb7d2a",
          "Name": "IsActive",
          "DisplayName": "IsActive",
          "Description": "System built-in field",
          "CreateTime": "2025-09-19T07:59:17.707Z",
          "UpdateTime": "2025-09-19T07:59:17.707Z",
          "SqlType": {
            "Name": "BIT",
            "LengthLimit": null,
            "MaxValue": null,
            "MinValue": null,
            "DecimalPrecision": null
          },
          "IsSystemField": true,
          "IsRequired": true,
          "ReferenceEntity": null,
          "ReferenceType": "ManyToOne",
          "FieldDisplayType": "Basic",
          "ReferenceChoiceSet": null,
          "IsAttachment": false
        },
        {
          "Id": "448bd5f9-1f88-4a9f-9ae1-8cabd0ffc9ad",
          "Name": "Email",
          "DisplayName": "E-mail",
          "Description": "System built-in field",
          "CreateTime": "2025-09-19T07:59:17.707Z",
          "UpdateTime": "2025-09-19T07:59:17.707Z",
          "SqlType": {
            "Name": "NVARCHAR",
            "LengthLimit": 512,
            "MaxValue": null,
            "MinValue": null,
            "DecimalPrecision": null
          },
          "IsSystemField": true,
          "IsRequired": false,
          "ReferenceEntity": null,
          "ReferenceType": "ManyToOne",
          "FieldDisplayType": "Basic",
          "ReferenceChoiceSet": null,
          "IsAttachment": false
        },
        {
          "Id": "22a340b7-a125-478c-ab64-ab8981154165",
          "Name": "UpdateTime",
          "DisplayName": "UpdateTime",
          "Description": "System built-in field",
          "CreateTime": "2025-09-19T07:59:17.707Z",
          "UpdateTime": "2025-09-19T07:59:17.707Z",
          "SqlType": {
            "Name": "DATETIMEOFFSET",
            "LengthLimit": null,
            "MaxValue": null,
            "MinValue": null,
            "DecimalPrecision": null
          },
          "IsSystemField": true,
          "IsRequired": false,
          "ReferenceEntity": null,
          "ReferenceType": "ManyToOne",
          "FieldDisplayType": "Basic",
          "ReferenceChoiceSet": null,
          "IsAttachment": false
        },
        {
          "Id": "7043687c-58bd-4e7c-91f7-c71f5d65ad61",
          "Name": "CreateTime",
          "DisplayName": "CreateTime",
          "Description": "System built-in field",
          "CreateTime": "2025-09-19T07:59:17.707Z",
          "UpdateTime": "2025-09-19T07:59:17.707Z",
          "SqlType": {
            "Name": "DATETIMEOFFSET",
            "LengthLimit": null,
            "MaxValue": null,
            "MinValue": null,
            "DecimalPrecision": null
          },
          "IsSystemField": true,
          "IsRequired": true,
          "ReferenceEntity": null,
          "ReferenceType": "ManyToOne",
          "FieldDisplayType": "Basic",
          "ReferenceChoiceSet": null,
          "IsAttachment": false
        },
        {
          "Id": "e349d138-fd23-48aa-bc48-f99d01faf422",
          "Name": "Name",
          "DisplayName": "Name",
          "Description": "System built-in field",
          "CreateTime": "2025-09-19T07:59:17.707Z",
          "UpdateTime": "2025-09-19T07:59:17.707Z",
          "SqlType": {
            "Name": "NVARCHAR",
            "LengthLimit": 512,
            "MaxValue": null,
            "MinValue": null,
            "DecimalPrecision": null
          },
          "IsSystemField": true,
          "IsRequired": true,
          "ReferenceEntity": null,
          "ReferenceType": "ManyToOne",
          "FieldDisplayType": "Basic",
          "ReferenceChoiceSet": null,
          "IsAttachment": false
        }
      ],
      "RecordCount": 6,
      "EntityType": "SystemEntity"
    }
  ],
  "Namespace": "Password_Restarter",
  "EntitiesJson": "{\"entities\":[{\"name\":\"Sontu\",\"displayName\":\"Sontu\",\"entityTypeId\":0,\"entityType\":\"Entity\",\"description\":\"\",\"fields\":[{\"id\":\"4bc0188a-2e95-f011-b3cd-002248a46af2\",\"name\":\"Name\",\"isPrimaryKey\":false,\"isForeignKey\":false,\"isExternalField\":false,\"isHiddenField\":false,\"fieldCategoryId\":0,\"isUnique\":false,\"referenceType\":\"ManyToOne\",\"sqlType\":{\"name\":\"NVARCHAR\",\"lengthLimit\":200},\"isRequired\":false,\"isEncrypted\":false,\"displayName\":\"Name\",\"description\":\"\",\"createTime\":\"2025-09-19T07:59:17.847Z\",\"createdBy\":\"6a8b4e4b-c3ab-4cd2-b61e-c79702a7f957\",\"updateTime\":\"2025-09-19T07:59:17.847Z\",\"updatedBy\":\"6a8b4e4b-c3ab-4cd2-b61e-c79702a7f957\",\"isSystemField\":false,\"isAttachment\":false,\"isRbacEnabled\":false,\"isModelReserved\":false},{\"id\":\"5482702c-8e70-47e4-a64f-57e9b88161cb\",\"name\":\"UpdateTime\",\"isPrimaryKey\":false,\"isForeignKey\":false,\"isExternalField\":false,\"isHiddenField\":false,\"fieldCategoryId\":0,\"isUnique\":false,\"referenceType\":\"ManyToOne\",\"sqlType\":{\"name\":\"DATETIMEOFFSET\"},\"isRequired\":false,\"isEncrypted\":false,\"displayName\":\"UpdateTime\",\"description\":\"System built-in field\",\"createTime\":\"2025-09-19T07:59:17.807Z\",\"createdBy\":\"6a8b4e4b-c3ab-4cd2-b61e-c79702a7f957\",\"updateTime\":\"2025-09-19T07:59:17.807Z\",\"isSystemField\":true,\"isAttachment\":false,\"isRbacEnabled\":false,\"isModelReserved\":false},{\"id\":\"baedab98-2444-441d-9c0c-a98488989811\",\"name\":\"Id\",\"isPrimaryKey\":true,\"isForeignKey\":false,\"isExternalField\":false,\"isHiddenField\":false,\"fieldCategoryId\":0,\"isUnique\":false,\"referenceType\":\"ManyToOne\",\"sqlType\":{\"name\":\"UNIQUEIDENTIFIER\"},\"isRequired\":true,\"isEncrypted\":false,\"displayName\":\"Id\",\"description\":\"System built-in field\",\"createTime\":\"2025-09-19T07:59:17.807Z\",\"createdBy\":\"6a8b4e4b-c3ab-4cd2-b61e-c79702a7f957\",\"updateTime\":\"2025-09-19T07:59:17.807Z\",\"isSystemField\":true,\"isAttachment\":false,\"isRbacEnabled\":false,\"isModelReserved\":false},{\"id\":\"66f16dde-5834-4539-b919-aee5074d1413\",\"name\":\"UpdatedBy\",\"isPrimaryKey\":false,\"isForeignKey\":true,\"isExternalField\":false,\"isHiddenField\":false,\"fieldCategoryId\":0,\"isUnique\":false,\"referenceName\":\"fk_UpdatedBy_726c9ae9-7958-4b63-a730-2d8845ef14f1\",\"referenceEntity\":{\"name\":\"SystemUser\",\"displayName\":\"System Users\",\"entityTypeId\":3,\"entityType\":\"SystemEntity\",\"isRbacEnabled\":false,\"invalidIdentifiers\":[],\"isModelReserved\":false,\"id\":\"39c0188a-2e95-f011-b3cd-002248a46af2\"},\"referenceField\":{\"id\":\"e349d138-fd23-48aa-bc48-f99d01faf422\",\"definition\":{\"name\":\"Name\",\"isPrimaryKey\":false,\"isForeignKey\":false,\"isExternalField\":false,\"isHiddenField\":false,\"fieldCategoryId\":0,\"isUnique\":false,\"referenceType\":\"ManyToOne\",\"sqlType\":{\"name\":\"NVARCHAR\",\"lengthLimit\":512},\"isRequired\":false,\"isEncrypted\":false,\"displayName\":\"Name\",\"createTime\":\"2025-09-19T07:59:38.685868Z\",\"updateTime\":\"2025-09-19T07:59:38.685868Z\",\"isSystemField\":false,\"isAttachment\":false,\"isRbacEnabled\":false,\"isModelReserved\":false}},\"referenceType\":\"ManyToOne\",\"sqlType\":{\"name\":\"UNIQUEIDENTIFIER\"},\"isRequired\":false,\"isEncrypted\":false,\"displayName\":\"UpdatedBy\",\"description\":\"System built-in field\",\"createTime\":\"2025-09-19T07:59:17.807Z\",\"createdBy\":\"6a8b4e4b-c3ab-4cd2-b61e-c79702a7f957\",\"updateTime\":\"2025-09-19T07:59:17.807Z\",\"isSystemField\":true,\"fieldDisplayType\":\"Relationship\",\"isAttachment\":false,\"isRbacEnabled\":false,\"isModelReserved\":false},{\"id\":\"b148a8da-08a7-4798-87b0-e38d8c0d92d1\",\"name\":\"CreateTime\",\"isPrimaryKey\":false,\"isForeignKey\":false,\"isExternalField\":false,\"isHiddenField\":false,\"fieldCategoryId\":0,\"isUnique\":false,\"referenceType\":\"ManyToOne\",\"sqlType\":{\"name\":\"DATETIMEOFFSET\"},\"isRequired\":true,\"isEncrypted\":false,\"displayName\":\"CreateTime\",\"description\":\"System built-in field\",\"createTime\":\"2025-09-19T07:59:17.807Z\",\"createdBy\":\"6a8b4e4b-c3ab-4cd2-b61e-c79702a7f957\",\"updateTime\":\"2025-09-19T07:59:17.807Z\",\"isSystemField\":true,\"isAttachment\":false,\"isRbacEnabled\":false,\"isModelReserved\":false},{\"id\":\"c9148bb7-5d6d-419c-9631-f5a7d37bb305\",\"name\":\"CreatedBy\",\"isPrimaryKey\":false,\"isForeignKey\":true,\"isExternalField\":false,\"isHiddenField\":false,\"fieldCategoryId\":0,\"isUnique\":false,\"referenceName\":\"fk_CreatedBy_96f581ea-522a-4f99-8a31-a2a97a3f3a76\",\"referenceEntity\":{\"name\":\"SystemUser\",\"displayName\":\"System Users\",\"entityTypeId\":3,\"entityType\":\"SystemEntity\",\"isRbacEnabled\":false,\"invalidIdentifiers\":[],\"isModelReserved\":false,\"id\":\"39c0188a-2e95-f011-b3cd-002248a46af2\"},\"referenceField\":{\"id\":\"e349d138-fd23-48aa-bc48-f99d01faf422\",\"definition\":{\"name\":\"Name\",\"isPrimaryKey\":false,\"isForeignKey\":false,\"isExternalField\":false,\"isHiddenField\":false,\"fieldCategoryId\":0,\"isUnique\":false,\"referenceType\":\"ManyToOne\",\"sqlType\":{\"name\":\"NVARCHAR\",\"lengthLimit\":512},\"isRequired\":false,\"isEncrypted\":false,\"displayName\":\"Name\",\"createTime\":\"2025-09-19T07:59:38.6858703Z\",\"updateTime\":\"2025-09-19T07:59:38.6858703Z\",\"isSystemField\":false,\"isAttachment\":false,\"isRbacEnabled\":false,\"isModelReserved\":false}},\"referenceType\":\"ManyToOne\",\"sqlType\":{\"name\":\"UNIQUEIDENTIFIER\"},\"isRequired\":true,\"isEncrypted\":false,\"displayName\":\"CreatedBy\",\"description\":\"System built-in field\",\"createTime\":\"2025-09-19T07:59:17.807Z\",\"createdBy\":\"6a8b4e4b-c3ab-4cd2-b61e-c79702a7f957\",\"updateTime\":\"2025-09-19T07:59:17.807Z\",\"isSystemField\":true,\"fieldDisplayType\":\"Relationship\",\"isAttachment\":false,\"isRbacEnabled\":false,\"isModelReserved\":false}],\"recordCount\":0,\"storageSizeInMB\":0.0,\"usedStorageSizeInMB\":0.0,\"isRbacEnabled\":false,\"invalidIdentifiers\":[],\"isModelReserved\":false,\"id\":\"41c0188a-2e95-f011-b3cd-002248a46af2\",\"createdBy\":\"6a8b4e4b-c3ab-4cd2-b61e-c79702a7f957\",\"createTime\":\"2025-09-19T07:59:17.79Z\",\"updateTime\":\"2025-09-19T07:59:17.843Z\",\"updatedBy\":\"6a8b4e4b-c3ab-4cd2-b61e-c79702a7f957\"},{\"name\":\"SystemUser\",\"displayName\":\"System Users\",\"entityTypeId\":3,\"entityType\":\"SystemEntity\",\"description\":\"Contains Automation Cloud users and groups that have ever had roles assigned, or accessed Data Service\",\"fields\":[{\"id\":\"ee9ea9d6-ce54-4202-91b1-537ab4cf1810\",\"name\":\"Id\",\"isPrimaryKey\":true,\"isForeignKey\":false,\"isExternalField\":false,\"isHiddenField\":false,\"fieldCategoryId\":0,\"isUnique\":false,\"referenceType\":\"ManyToOne\",\"sqlType\":{\"name\":\"UNIQUEIDENTIFIER\"},\"isRequired\":true,\"isEncrypted\":false,\"displayName\":\"Id\",\"description\":\"System built-in field\",\"createTime\":\"2025-09-19T07:59:17.707Z\",\"createdBy\":\"6a8b4e4b-c3ab-4cd2-b61e-c79702a7f957\",\"updateTime\":\"2025-09-19T07:59:17.707Z\",\"isSystemField\":true,\"isAttachment\":false,\"isRbacEnabled\":false,\"isModelReserved\":false},{\"id\":\"e0bcda61-3641-45f3-98c9-6c251420ee25\",\"name\":\"Type\",\"isPrimaryKey\":false,\"isForeignKey\":false,\"isExternalField\":false,\"isHiddenField\":false,\"fieldCategoryId\":0,\"isUnique\":false,\"referenceChoiceSet\":{\"name\":\"UserType\",\"entityTypeId\":0,\"entityType\":\"Entity\",\"isRbacEnabled\":false,\"invalidIdentifiers\":[],\"isModelReserved\":false},\"referenceType\":\"ManyToOne\",\"sqlType\":{\"name\":\"INT\",\"maxValue\":9007199254740991.0,\"minValue\":-9007199254740991.0},\"isRequired\":true,\"isEncrypted\":false,\"displayName\":\"Type\",\"description\":\"System built-in field\",\"createTime\":\"2025-09-19T07:59:17.707Z\",\"createdBy\":\"6a8b4e4b-c3ab-4cd2-b61e-c79702a7f957\",\"updateTime\":\"2025-09-19T07:59:17.707Z\",\"isSystemField\":true,\"fieldDisplayType\":\"ChoiceSetSingle\",\"choiceSetId\":\"32c0188a-2e95-f011-b3cd-002248a46af2\",\"isAttachment\":false,\"isRbacEnabled\":false,\"isModelReserved\":false},{\"id\":\"02ec56e9-d074-4c74-ad80-6e19c2fb7d2a\",\"name\":\"IsActive\",\"isPrimaryKey\":false,\"isForeignKey\":false,\"isExternalField\":false,\"isHiddenField\":false,\"fieldCategoryId\":0,\"isUnique\":false,\"referenceType\":\"ManyToOne\",\"sqlType\":{\"name\":\"BIT\"},\"isRequired\":true,\"isEncrypted\":false,\"displayName\":\"IsActive\",\"description\":\"System built-in field\",\"createTime\":\"2025-09-19T07:59:17.707Z\",\"createdBy\":\"6a8b4e4b-c3ab-4cd2-b61e-c79702a7f957\",\"updateTime\":\"2025-09-19T07:59:17.707Z\",\"isSystemField\":true,\"isAttachment\":false,\"isRbacEnabled\":false,\"isModelReserved\":false},{\"id\":\"448bd5f9-1f88-4a9f-9ae1-8cabd0ffc9ad\",\"name\":\"Email\",\"isPrimaryKey\":false,\"isForeignKey\":false,\"isExternalField\":false,\"isHiddenField\":false,\"fieldCategoryId\":0,\"isUnique\":false,\"referenceType\":\"ManyToOne\",\"sqlType\":{\"name\":\"NVARCHAR\",\"lengthLimit\":512},\"isRequired\":false,\"isEncrypted\":false,\"displayName\":\"E-mail\",\"description\":\"System built-in field\",\"createTime\":\"2025-09-19T07:59:17.707Z\",\"createdBy\":\"6a8b4e4b-c3ab-4cd2-b61e-c79702a7f957\",\"updateTime\":\"2025-09-19T07:59:17.707Z\",\"isSystemField\":true,\"isAttachment\":false,\"isRbacEnabled\":false,\"isModelReserved\":false},{\"id\":\"22a340b7-a125-478c-ab64-ab8981154165\",\"name\":\"UpdateTime\",\"isPrimaryKey\":false,\"isForeignKey\":false,\"isExternalField\":false,\"isHiddenField\":false,\"fieldCategoryId\":0,\"isUnique\":false,\"referenceType\":\"ManyToOne\",\"sqlType\":{\"name\":\"DATETIMEOFFSET\"},\"isRequired\":false,\"isEncrypted\":false,\"displayName\":\"UpdateTime\",\"description\":\"System built-in field\",\"createTime\":\"2025-09-19T07:59:17.707Z\",\"createdBy\":\"6a8b4e4b-c3ab-4cd2-b61e-c79702a7f957\",\"updateTime\":\"2025-09-19T07:59:17.707Z\",\"isSystemField\":true,\"isAttachment\":false,\"isRbacEnabled\":false,\"isModelReserved\":false},{\"id\":\"7043687c-58bd-4e7c-91f7-c71f5d65ad61\",\"name\":\"CreateTime\",\"isPrimaryKey\":false,\"isForeignKey\":false,\"isExternalField\":false,\"isHiddenField\":false,\"fieldCategoryId\":0,\"isUnique\":false,\"referenceType\":\"ManyToOne\",\"sqlType\":{\"name\":\"DATETIMEOFFSET\"},\"isRequired\":true,\"isEncrypted\":false,\"displayName\":\"CreateTime\",\"description\":\"System built-in field\",\"createTime\":\"2025-09-19T07:59:17.707Z\",\"createdBy\":\"6a8b4e4b-c3ab-4cd2-b61e-c79702a7f957\",\"updateTime\":\"2025-09-19T07:59:17.707Z\",\"isSystemField\":true,\"isAttachment\":false,\"isRbacEnabled\":false,\"isModelReserved\":false},{\"id\":\"e349d138-fd23-48aa-bc48-f99d01faf422\",\"name\":\"Name\",\"isPrimaryKey\":false,\"isForeignKey\":false,\"isExternalField\":false,\"isHiddenField\":false,\"fieldCategoryId\":0,\"isUnique\":false,\"referenceType\":\"ManyToOne\",\"sqlType\":{\"name\":\"NVARCHAR\",\"lengthLimit\":512},\"isRequired\":true,\"isEncrypted\":false,\"displayName\":\"Name\",\"description\":\"System built-in field\",\"createTime\":\"2025-09-19T07:59:17.707Z\",\"createdBy\":\"6a8b4e4b-c3ab-4cd2-b61e-c79702a7f957\",\"updateTime\":\"2025-09-19T07:59:17.707Z\",\"isSystemField\":true,\"isAttachment\":false,\"isRbacEnabled\":false,\"isModelReserved\":false}],\"recordCount\":6,\"storageSizeInMB\":0.070312,\"usedStorageSizeInMB\":0.015625,\"isRbacEnabled\":false,\"invalidIdentifiers\":[],\"isModelReserved\":false,\"id\":\"39c0188a-2e95-f011-b3cd-002248a46af2\",\"createdBy\":\"6a8b4e4b-c3ab-4cd2-b61e-c79702a7f957\",\"createTime\":\"2025-09-19T07:59:17.69Z\",\"updateTime\":\"2025-09-19T07:59:17.69Z\",\"updatedBy\":\"6a8b4e4b-c3ab-4cd2-b61e-c79702a7f957\"}],\"choicesets\":[{\"id\":\"32c0188a-2e95-f011-b3cd-002248a46af2\",\"name\":\"UserType\",\"displayName\":\"User Type\",\"description\":\"Denotes the type of user record in the System User entity\",\"createdBy\":\"6a8b4e4b-c3ab-4cd2-b61e-c79702a7f957\",\"createTime\":\"2025-09-19T07:59:17.637Z\",\"updateTime\":\"2025-09-19T07:59:17.637Z\",\"updatedBy\":\"6a8b4e4b-c3ab-4cd2-b61e-c79702a7f957\",\"isModelReserved\":false,\"data\":[{\"DisplayName\":\"Group\",\"Name\":\"Group\",\"NumberId\":1},{\"DisplayName\":\"Robot\",\"Name\":\"Robot\",\"NumberId\":2},{\"DisplayName\":\"User\",\"Name\":\"User\",\"NumberId\":0},{\"DisplayName\":\"Application\",\"Name\":\"Application\",\"NumberId\":3}]}]}",
  "SelectedEntitiesNames": [
    "Sontu",
    "SystemUser"
  ]
}